mcp_pyautogui_server/__init__.py
mcp_pyautogui_server/__main__.py
mcp_pyautogui_server/server.py
mcp_pyautogui_server-0.1.2.dist-info/METADATA
mcp_pyautogui_server-0.1.2.dist-info/WHEEL
mcp_pyautogui_server-0.1.2.dist-info/entry_points.txt
mcp_pyautogui_server-0.1.2.dist-info/licenses/LICENSE
mcp_pyautogui_server-0.1.2.dist-info/RECORD
