Metadata-Version: 2.4
Name: mcp-pyautogui-server
Version: 0.1.2
Summary: MCP server for pyautogui
Author-email: He Tao <hetao7@pku.edu.cn>
License: MIT
License-File: LICENSE
Keywords: automation,gui,mcp,pyautogui
Classifier: Development Status :: 4 - Beta
Classifier: Intended Audience :: Developers
Classifier: License :: OSI Approved :: MIT License
Classifier: Programming Language :: Python :: 3
Classifier: Programming Language :: Python :: 3.12
Requires-Python: >=3.10
Requires-Dist: fastmcp>=0.4.1
Requires-Dist: pillow>=11.1.0
Requires-Dist: pyautogui>=0.9.54
